nas/__init__.py
nas/version.py
nas-0.1.0.dist-info/METADATA
nas-0.1.0.dist-info/WHEEL
nas-0.1.0.dist-info/top_level.txt
nas-0.1.0.dist-info/RECORD
