Metadata-Version: 2.1
Name: nas
Version: 0.1.0
Summary: a package of network architecture search
Home-page: http://github.com/zhiqingxiao/nas/
Author: Zhiqing Xiao
Author-email: xzq.xiaozhiqing@gmail.com
Classifier: Programming Language :: Python
Classifier: Intended Audience :: Science/Research
